mpe/__init__.py
mpe/mcp_client.py
mpe/server.py
mcp_proxy_exec-0.1.6.dist-info/METADATA
mcp_proxy_exec-0.1.6.dist-info/WHEEL
mcp_proxy_exec-0.1.6.dist-info/entry_points.txt
mcp_proxy_exec-0.1.6.dist-info/top_level.txt
mcp_proxy_exec-0.1.6.dist-info/RECORD
